cdotenv/__init__.py
cdotenv/cdotenv.py
cdotenv-0.1.6.dist-info/licenses/LICENSE
cdotenv-0.1.6.dist-info/METADATA
cdotenv-0.1.6.dist-info/WHEEL
cdotenv-0.1.6.dist-info/top_level.txt
cdotenv-0.1.6.dist-info/RECORD
