Metadata-Version: 2.4
Name: cdotenv
Version: 0.1.6
Summary: Load and access environment variables with type casting
Author-email: "(gcca)" <git@gcca.dev>
License-Expression: GPL-3.0-or-later
Project-URL: Homepage, https://github.com/gcca/cdotenv
Project-URL: Repository, https://github.com/gcca/cdotenv.git
Project-URL: Issues, https://github.com/gcca/cdotenv/issues
Classifier: Programming Language :: Python :: 3
Classifier: Programming Language :: Python :: 3.13
Classifier: Operating System :: OS Independent
Requires-Python: >=3.8
License-File: LICENSE
Dynamic: license-file
